[
    {
        "value": 5537.14,
        "ccy": "CHF",
        "date": "2024-05-24",
        "rate": 4.2912
    },
    {
        "value": 5442.5,
        "ccy": "CHF",
        "date": "2024-03-21",
        "rate": 4.4
    },
    {
        "value": 3844.42,
        "ccy": "CHF",
        "date": "2024-02-14",
        "rate": 4.5
    },
    {
        "value": 13456.31,
        "ccy": "CHF",
        "date": "2024-01-16",
        "rate": 4.67
    },
    {
        "value": 2298.82,
        "ccy": "CHF",
        "date": "2023-12-08",
        "rate": 4.574
    },
    {
        "value": 4395.6,
        "ccy": "CHF",
        "date": "2023-11-15",
        "rate": 4.55
    },
    {
        "value": 5010,
        "ccy": "CHF",
        "date": "2023-05-16",
        "rate": 4.621
    },
    {
        "value": 3006,
        "ccy": "CHF",
        "date": "2023-03-16",
        "rate": 4.7775
    },
    {
        "value": 1914.02,
        "ccy": "CHF",
        "date": "2023-03-16",
        "rate": 4.7866
    },
    {
        "value": 3483.54,
        "ccy": "CHF",
        "date": "2025-01-07",
        "rate": 4.5150
    }
]